lsstprojectmeta/__init__.py
lsstprojectmeta/jsonld.py
lsstprojectmeta/ltd.py
lsstprojectmeta/cli/__init__.py
lsstprojectmeta/cli/ingestdocs.py
lsstprojectmeta/data/githubv4/README.rst
lsstprojectmeta/data/githubv4/technote_repo.graphql
lsstprojectmeta/git/__init__.py
lsstprojectmeta/git/timestamp.py
lsstprojectmeta/github/__init__.py
lsstprojectmeta/github/auth.py
lsstprojectmeta/github/graphql.py
lsstprojectmeta/github/urls.py
lsstprojectmeta/lsstdocument/__init__.py
lsstprojectmeta/lsstdocument/handles.py
lsstprojectmeta/lsstdocument/lander.py
lsstprojectmeta/lsstdocument/sphinxtechnotes.py
lsstprojectmeta/pandoc/__init__.py
lsstprojectmeta/pandoc/convert.py
lsstprojectmeta/pandoc/filters/__init__.py
lsstprojectmeta/pandoc/filters/deparagraph.py
lsstprojectmeta/tex/__init__.py
lsstprojectmeta/tex/citelink.py
lsstprojectmeta/tex/commandparser.py
lsstprojectmeta/tex/lsstbib.py
lsstprojectmeta/tex/lsstdoc.py
lsstprojectmeta/tex/lsstmacros.py
lsstprojectmeta/tex/normalizer.py
lsstprojectmeta/tex/scraper.py
lsst_projectmeta_kit-0.3.6.dist-info/LICENSE
lsst_projectmeta_kit-0.3.6.dist-info/METADATA
lsst_projectmeta_kit-0.3.6.dist-info/WHEEL
lsst_projectmeta_kit-0.3.6.dist-info/entry_points.txt
lsst_projectmeta_kit-0.3.6.dist-info/top_level.txt
lsst_projectmeta_kit-0.3.6.dist-info/RECORD
