Metadata-Version: 2.1
Name: lsst-projectmeta-kit
Version: 0.3.6
Summary: Python toolkit for extracting and transforming metadata about LSST's code and documentation projects, and loading it into the LSST projectmeta database.
Home-page: https://github.com/lsst-sqre/lsst-projectmeta-kit
Author: Association of Universities for Research in Astronomy, Inc.
Author-email: jsick@lsst.org
License: MIT
Keywords: lsst
Platform: UNKNOWN
Classifier: Development Status :: 4 - Beta
Classifier: License :: OSI Approved :: MIT License
Classifier: Programming Language :: Python :: 3.5
Classifier: Programming Language :: Python :: 3.6
Requires-Dist: pyjwt (>=1.4.2)
Requires-Dist: requests (>=2.13.0)
Requires-Dist: pypandoc (>=1.4)
Requires-Dist: panflute (==1.10.6)
Requires-Dist: aiohttp (>=2.2.5)
Requires-Dist: pybtex (>=0.21)
Requires-Dist: GitPython (>=2.1.7)
Requires-Dist: pytz
Requires-Dist: motor (<1.3.0,>=1.2.0)
Requires-Dist: attrs (>=17.4.0)
Provides-Extra: dev
Requires-Dist: pytest (==4.4.0) ; extra == 'dev'
Requires-Dist: pytest-cov (==2.6.1) ; extra == 'dev'
Requires-Dist: pytest-flake8 (==1.0.4) ; extra == 'dev'
